pancakekit/__init__.py
pancakekit/__main__.py
pancakekit/_version.py
pancakekit/pancakekit.py
pancakekit/basecomponent/__init__.py
pancakekit/basecomponent/navigation.py
pancakekit/static/css/pancake.css
pancakekit/static/css/w3.css
pancakekit/static/js/draggable.js
pancakekit/static/js/main.js
pancakekit/static/js/run_script.js
pancakekit/toppings/__init__.py
pancakekit/toppings/automatic.py
pancakekit/toppings/basic.py
pancakekit/toppings/image.py
pancakekit/toppings/nparray.py
pancakekit/toppings/table.py
pancakekit/utils/__init__.py
pancakekit/utils/utils.py
pancakekit-0.2.1.dist-info/LICENSE.txt
pancakekit-0.2.1.dist-info/METADATA
pancakekit-0.2.1.dist-info/WHEEL
pancakekit-0.2.1.dist-info/top_level.txt
pancakekit-0.2.1.dist-info/RECORD
