Metadata-Version: 2.1
Name: pancakekit
Version: 0.2.1
Summary: Handy graphical user interface library for daily use
Home-page: https://github.com/chocolate-icecream/pancakekit
Author: chocolate-icecream
Project-URL: Bug Tracker, https://github.com/chocolate-icecream/pancakekit/issues
Keywords: gui
Classifier: Programming Language :: Python :: 3
Classifier: Programming Language :: Python :: 3.8
Classifier: Programming Language :: Python :: 3.9
Classifier: Programming Language :: Python :: 3.10
Classifier: Programming Language :: Python :: 3 :: Only
Classifier: License :: OSI Approved :: MIT License
Classifier: Operating System :: OS Independent
Classifier: Development Status :: 3 - Alpha
Classifier: Intended Audience :: Science/Research
Classifier: Intended Audience :: Developers
Classifier: Intended Audience :: Education
Classifier: Topic :: Software Development :: User Interfaces
Requires-Python: >=3.8
License-File: LICENSE.txt
Requires-Dist: flask (>=2.1)
Requires-Dist: jinja2 (>=3.0)
Requires-Dist: pillow (>=8.1)
